markdown_spaces_generator/__init__.py
markdown_spaces_generator/cli.py
markdown_spaces_generator-0.3.1.dist-info/entry_points.txt
markdown_spaces_generator-0.3.1.dist-info/WHEEL
markdown_spaces_generator-0.3.1.dist-info/METADATA
markdown_spaces_generator-0.3.1.dist-info/RECORD
