Metadata-Version: 2.1
Name: markdown-spaces-generator
Version: 0.3.1
Summary: 
Author: 0djentd
Requires-Python: >=3.10,<4.0
Classifier: Programming Language :: Python :: 3
Classifier: Programming Language :: Python :: 3.10
Requires-Dist: click (>=8.1.3,<9.0.0)
